DataMemory.v
`timescale 1ns / 1ps

`define SIZE 1024
`timescale 1ns / 1ps

module DataMemory(ReadData , Address , WriteData , MemoryRead , MemoryWrite , Clock);
   input [63:0]      WriteData;
   input [63:0]      Address;
   input             Clock, MemoryRead, MemoryWrite;
   output reg [63:0] ReadData;

   reg [7:0] 	     memBank [`SIZE-1:0];


   // This task is used to write arbitrary data to the Data Memory by
   // the intialization block.
   task initset;
      input [63:0] addr;
      input [63:0] data;
      begin
	 memBank[addr] =  data[63:56] ; // Big-endian for the win...
	 memBank[addr+1] =  data[55:48];
	 memBank[addr+2] =  data[47:40];
	 memBank[addr+3] =  data[39:32];
	 memBank[addr+4] =  data[31:24];
	 memBank[addr+5] =  data[23:16];
	 memBank[addr+6] =  data[15:8];
	 memBank[addr+7] =  data[7:0];
      end
   endtask


   initial
     begin
        // preseting some data in the data memory used by test #1

        // Address 0x0 gets 0x1
        initset( 64'h0,  64'h1);  //Counter variable
        initset( 64'h8,  64'ha);  //Part of mask
        initset( 64'h10, 64'h5);  //Other part of mask
        initset( 64'h18, 64'h0ffbea7deadbeeff); //big constant
        initset( 64'h20, 64'h0); //clearing space

        // Add any data you need for your tests here.

     end

   // This always block reads the data memory and places a double word
   // on the ReadData bus.
   always @(posedge Clock)
     begin
        if(MemoryRead)
          begin
             ReadData[63:56] <=  memBank[Address];
             ReadData[55:48] <=  memBank[Address+1];
             ReadData[47:40] <=  memBank[Address+2];
             ReadData[39:32] <=  memBank[Address+3];
             ReadData[31:24] <=  memBank[Address+4];
             ReadData[23:16] <=  memBank[Address+5];
             ReadData[15:8] <=  memBank[Address+6];
             ReadData[7:0] <=  memBank[Address+7];
          end
     end

   // This always block takes data from the WriteData bus and writes
   // it into the DataMemory.
   always @(posedge Clock)
     begin
        if(MemoryWrite)
          begin
             memBank[Address] <= #3 WriteData[63:56] ;
             memBank[Address+1] <= #3 WriteData[55:48];
             memBank[Address+2] <= #3 WriteData[47:40];
             memBank[Address+3] <= #3 WriteData[39:32];
             memBank[Address+4] <= #3 WriteData[31:24];
             memBank[Address+5] <= #3 WriteData[23:16];
             memBank[Address+6] <= #3 WriteData[15:8];
             memBank[Address+7] <= #3 WriteData[7:0];
             // Could be useful for debugging:
             // $display("Writing Address:%h Data:%h",Address, WriteData);
          end
     end
endmodule

NextPClogic.v
`timescale 1ns / 1ps

module NextPClogic(NextPC, CurrentPC, SignExtImm64, Branch, ALUZero, Uncondbranch); 
   input [63:0] CurrentPC, SignExtImm64; 
   input 	Branch, ALUZero, Uncondbranch; 
   
   output reg [63:0] NextPC; 

   // when uncondbranch, directly add the SignExtImm64 to the CurrentPC
   // when Branch is conditional and when the ALU input is also 1, you will take the branch and the next PC will be calculated by adding the SignExtImm64 to the CurrentPC
   // when neither, increment PC by 4

   always @(*) begin
        if (Uncondbranch) begin NextPC = CurrentPC + (SignExtImm64 << 2); end
        else if (Branch && ALUZero) begin NextPC = CurrentPC + (SignExtImm64 << 2); end
        else begin NextPC = CurrentPC + 4; end
   end

endmodule

ALU.v
`timescale 1ns / 1ps

`define AND   4'b0000
`define OR    4'b0001
`define ADD   4'b0010
`define SUB   4'b0110
`define PassB 4'b0111


module ALU(BusW, BusA, BusB, ALUCtrl, Zero);
    
    output  [63:0] BusW;
    input   [63:0] BusA, BusB;
    input   [3:0] ALUCtrl;
    output  Zero;
    
    reg     [63:0] BusW;
    
    always @(ALUCtrl or BusA or BusB) begin        
        case(ALUCtrl)
            `AND: begin
                BusW = BusA & BusB;
            end
            `OR: begin
                BusW = BusA | BusB;
            end
            `ADD: begin
                BusW = BusA + BusB;
            end
            `SUB: begin
                BusW = BusA - BusB;
            end
            `PassB: begin
                BusW = BusB;
            end
        endcase
        $display("OP %h, BusA = %h, BusB = %h, BusW = %h", ALUCtrl, BusA, BusB, BusW);
    end

    assign Zero = (BusW == 64'b0);
endmodule

RegisterFile.v
`timescale 1ns / 1ps

module RegisterFile(BusA, BusB, BusW, RW, RA, RB, RegWr, Clk);
    output [63:0] BusA;
    output [63:0] BusB;
    input [63:0] BusW;
    input [4:0] RW;
    input [4:0] RA;
    input [4:0] RB;
    input RegWr;
    input Clk;
    reg [63:0] registers [31:0];
     
    //assign #2 BusA = registers[RA];
    //assign #2 BusB = registers[RB];
    
    // use ternary operator to make A and B 0 when RA or RB 
    //assign BusA = RA || RB ? 0 : 1;
    //assign BusB = RA || RB ? 0 : 1;
     
    always @ (negedge Clk) begin
        if(RegWr)
            if (RW != 31) registers[RW] <= #3 BusW;
    end
    
    assign #2 BusA = RA == 31 ? 0 : registers[RA];
    assign #2 BusB = RB == 31 ? 0 : registers[RB];
    
    /*
    always (RA) begin
        if (RA == 31 #2 
            BusA = 0;
        else #2 
            BusA = registers[RA];
    end
    always (RB) begin
        if (RB == 31 #2 
            BusB = 0;
        else #2 
            BusB = registers[RB];
    end
    */
    
endmodule

SignExtender.v
`timescale 1ns / 1ps

module SignExtender(OutBus, Imm26, Ctrl); 
   output reg [63:0] OutBus; 
   input [25:0]  Imm26; 
   input [2:0] Ctrl; 
   
   always@ (Ctrl, Imm26)
    begin
      case (Ctrl)
        // I-type, 12 bits in bus from [21:10], ALU extended to 64 bits
        3'b000: 
                begin
                OutBus = {{52{1'b0}}, Imm26[21:10]};
                //$display("00 Imm26[25] = %h, Imm26 = %x", Imm26[25], Imm26);
               end
        
        // D-type, 9 bits in bus from [20:12], ALU extended to 64 bits
        3'b001: begin
                OutBus = {{55{Imm26[20]}}, Imm26[20:12]}; 
                //$display("01 Imm26[25] = %h, Imm26 = %x", Imm26[25], Imm26);
               end
        
        // B, 26 bits that was entire bus, ALU extended to 64 bits, padded 2 0's to shift left
        3'b010: begin
               OutBus = {{38{Imm26[25]}}, Imm26[25:0]};
               //$display("10 Imm26[25] = %h, Imm26 = %x", Imm26[25], Imm26);
               end
        
        // CB, 19 bits in bus from [23:5], ALU extended to 64 bits, padded 2 0's to shift left
        3'b011: begin
                OutBus = {{45{Imm26[23]}}, Imm26[23:5]};
                //$display("11 Imm26[25] = %h, Imm26 = %x", Imm26[25], Imm26);
               end
        // MOVZ 0 bits
        3'b100:
                begin
                OutBus = Imm26[20:5] << (Imm26[22:21] * 16);
                $display("outbus = %h, Imm26 = %h", OutBus, Imm26);
               end
      endcase
    end
endmodule

SingleCycleControl.v
`timescale 1ns / 1ps

`define OPCODE_ANDREG 11'b?0001010???
`define OPCODE_ORRREG 11'b?0101010???
`define OPCODE_ADDREG 11'b?0?01011???
`define OPCODE_SUBREG 11'b?1?01011???

`define OPCODE_ADDIMM 11'b?0?10001???
`define OPCODE_SUBIMM 11'b?1?10001???

`define OPCODE_MOVZ   11'b110100101??

`define OPCODE_B      11'b?00101?????
`define OPCODE_CBZ    11'b?011010????

`define OPCODE_LDUR   11'b??111000010
`define OPCODE_STUR   11'b??111000000

module control(
	       output reg 	reg2loc,
	       output reg 	alusrc,
	       output reg 	mem2reg,
	       output reg 	regwrite,
	       output reg 	memread,
	       output reg 	memwrite,
	       output reg 	branch,
	       output reg 	uncond_branch,
	       output reg [3:0] aluop,
	       output reg [2:0] signop,
	       input [10:0] 	opcode
	       );

   always @(*)
     begin
	casez (opcode)

          /* Add cases here for each instruction your processor supports */
	  `OPCODE_LDUR:
	    begin
	       reg2loc       = 1'bx;
               alusrc        = 1'b1;
               mem2reg       = 1'b1;
               regwrite      = 1'b1;
               memread       = 1'b1;
               memwrite      = 1'b0;
               branch        = 1'b0;
               uncond_branch = 1'b0;
               aluop         = 4'b0010;
               signop        = 3'b001;
	    end	  
	  
	  `OPCODE_STUR:
	    begin
	       reg2loc       = 1'b1;
               alusrc        = 1'b1;
               mem2reg       = 1'bx;
               regwrite      = 1'b0;
               memread       = 1'b0;
               memwrite      = 1'b1;
               branch        = 1'b0;
               uncond_branch = 1'b0;
               aluop         = 4'b0010;
               signop        = 3'b001;
	    end
	  
	  `OPCODE_ADDREG:
	    begin
	       reg2loc       = 1'b0;
               alusrc        = 1'b0;
               mem2reg       = 1'b0;
               regwrite      = 1'b1;
               memread       = 1'b0;
               memwrite      = 1'b0;
               branch        = 1'b0;
               uncond_branch = 1'b0;
               aluop         = 4'b0010;
               signop        = 3'b0xx;
	    end
	  
	  `OPCODE_SUBREG:
	    begin
	       reg2loc       = 1'b0;
               alusrc        = 1'b0;
               mem2reg       = 1'b0;
               regwrite      = 1'b1;
               memread       = 1'b0;
               memwrite      = 1'b0;
               branch        = 1'b0;
               uncond_branch = 1'b0;
               aluop         = 4'b0110;
               signop        = 3'bxxx;
	    end
	  
	  `OPCODE_ADDIMM:
	    begin
	       reg2loc       = 1'bx;
               alusrc        = 1'b1;
               mem2reg       = 1'b0;
               regwrite      = 1'b1;
               memread       = 1'b0;
               memwrite      = 1'b0;
               branch        = 1'b0;
               uncond_branch = 1'b0;
               aluop         = 4'b0010;
               signop        = 3'b000;
	    end
	  
	  `OPCODE_SUBIMM:
	    begin
	       reg2loc       = 1'bx;
               alusrc        = 1'b1;
               mem2reg       = 1'b0;
               regwrite      = 1'b1;
               memread       = 1'b0;
               memwrite      = 1'b0;
               branch        = 1'b0;
               uncond_branch = 1'b0;
               aluop         = 4'b0110;
               signop        = 3'b000;
	    end
	  
	  `OPCODE_ANDREG:
	    begin
	       reg2loc       = 1'b0;
               alusrc        = 1'b0;
               mem2reg       = 1'b0;
               regwrite      = 1'b1;
               memread       = 1'b0;
               memwrite      = 1'b0;
               branch        = 1'b0;
               uncond_branch = 1'b0;
               aluop         = 4'b0000;
               signop        = 3'bxxx;
	    end

	  `OPCODE_ORRREG:
	    begin
	       reg2loc       = 1'b0;
               alusrc        = 1'b0;
               mem2reg       = 1'b0;
               regwrite      = 1'b1;
               memread       = 1'b0;
               memwrite      = 1'b0;
               branch        = 1'b0;
               uncond_branch = 1'b0;
               aluop         = 4'b0001;
               signop        = 3'bxxx;
	    end
	  	  
	  `OPCODE_CBZ:
	    begin
	       reg2loc       = 1'b1;
               alusrc        = 1'b0;
               mem2reg       = 1'bx;
               regwrite      = 1'b0;
               memread       = 1'b0;
               memwrite      = 1'b0;
               branch        = 1'b1;
               uncond_branch = 1'b0;
               aluop         = 4'b0111;
               signop        = 3'b011;
	    end

	  
	  `OPCODE_B:
	    begin
	       reg2loc       = 1'bx;
               alusrc        = 1'bx;
               mem2reg       = 1'bx;
               regwrite      = 1'b0;
               memread       = 1'b0;
               memwrite      = 1'b0;
               branch        = 1'bx;
               uncond_branch = 1'b1;
               aluop         = 4'bxxxx;
               signop        = 3'b010;
	    end
	    
	  `OPCODE_MOVZ:
	    begin
	       reg2loc       = 1'bx;
               alusrc        = 1'b1;
               mem2reg       = 1'b0;
               regwrite      = 1'b1;
               memread       = 1'b0;
               memwrite      = 1'b0;
               branch        = 1'bx;
               uncond_branch = 1'b0;
               aluop         = 4'b0111;
               signop        = 3'b100;
	    end
	

          default:
            begin
               reg2loc       = 1'bx;
               alusrc        = 1'bx;
               mem2reg       = 1'bx;
               regwrite      = 1'b0;
               memread       = 1'b0;
               memwrite      = 1'b0;
               branch        = 1'b0;
               uncond_branch = 1'b0;
               aluop         = 4'bxxxx;
               signop        = 3'bxxx;
            end
	endcase
     end

endmodule

InstructionMemory.v
`timescale 1ns / 1ps
/*
 * Module: InstructionMemory
 *
 * Implements read-only instruction memory
 * 
 */
module InstructionMemory(Data, Address);
   parameter T_rd = 20;
   parameter MemSize = 40;
   
   output [31:0] Data;
   input [63:0]  Address;
   reg [31:0] 	 Data;
   
   /*
    * ECEN 350 Processor Test Functions
    * Texas A&M University
    */
   
   always @ (Address) begin

      case(Address)

	/* Test Program 1:
	 * Program loads constants from the data memory. Uses these constants to test
	 * the following instructions: LDUR, ORR, AND, CBZ, ADD, SUB, STUR and B.
	 * 
	 * Assembly code for test:
	 * 
	 * 0: LDUR X9, [XZR, 0x0]    //Load 1 into x9
	 * 4: LDUR X10, [XZR, 0x8]   //Load a into x10
	 * 8: LDUR X11, [XZR, 0x10]  //Load 5 into x11
	 * C: LDUR X12, [XZR, 0x18]  //Load big constant into x12
	 * 10: LDUR X13, [XZR, 0x20]  //load a 0 into X13
	 * 
	 * 14: ORR X10, X10, X11  //Create mask of 0xf
	 * 18: AND X12, X12, X10  //Mask off low order bits of big constant
	 * 
	 * loop:
	 * 1C: CBZ X12, end  //while X12 is not 0
	 * 20: ADD X13, X13, X9  //Increment counter in X13
	 * 24: SUB X12, X12, X9  //Decrement remainder of big constant in X12
	 * 28: B loop  //Repeat till X12 is 0
	 * 2C: STUR X13, [XZR, 0x20]  //store back the counter value into the memory location 0x20
	 */
	

	63'h000: Data = 32'hF84003E9;
	63'h004: Data = 32'hF84083EA;
	63'h008: Data = 32'hF84103EB;
	63'h00c: Data = 32'hF84183EC;
	63'h010: Data = 32'hF84203ED;
	63'h014: Data = 32'hAA0B014A;
	63'h018: Data = 32'h8A0A018C;
	63'h01c: Data = 32'hB400008C;
	63'h020: Data = 32'h8B0901AD;
	63'h024: Data = 32'hCB09018C;
	63'h028: Data = 32'h17FFFFFD;
	63'h02c: Data = 32'hF80203ED;
	63'h030: Data = 32'hF84203ED;  //One last load to place stored value on memdbus for test checking.

	/* Add code for your tests here */
	
	/*	
		MOVZ X9, 0xdef0, 0
		MOVZ X10, 0x9abc, 16
		MOVZ X11, 0x5678, 32
		MOVZ X12, 0x1234, 48
		
		ADD X13, XZR, XZR
		ADD X13, X13, X9
		ADD X13, X13, X10
		ADD X13, X13, X11
		ADD X13, X13, X12
				
		STUR X13, [XZR, 0x0]
		LDUR X13, [XZR, 0x0]
		
	*/
	63'h034: Data = {9'b110100101, 2'b00, 16'hdef0, 5'd9}; //32'h1A5DEF09;
	63'h038: Data = {9'b110100101, 2'b01, 16'h9abc, 5'd10}; //32'h1A59ABCA;
	63'h03c: Data = {9'b110100101, 2'b10, 16'h5678, 5'd11}; //32'h1A55678B;
	63'h040: Data = {9'b110100101, 2'b11, 16'h1234, 5'd12}; //32'h1A51234C;
	
	63'h044: Data = {11'b10001011000, 5'd31, 6'b0, 5'd31, 5'd13}; //32'b10001011000010100000000100101101;
	63'h048: Data = {11'b10001011000, 5'd9, 6'b0, 5'd13, 5'd13}; //32'b10001011000011010000000101101101;
	63'h04c: Data = {11'b10001011000, 5'd10, 6'b0, 5'd13, 5'd13}; //32'b10001011000011010000000110001101;
	63'h050: Data = {11'b10001011000, 5'd11, 6'b0, 5'd13, 5'd13};
	63'h054: Data = {11'b10001011000, 5'd12, 6'b0, 5'd13, 5'd13};
	
	63'h058: Data = {11'b11111000000, 9'b0, 2'b0, 5'd31, 5'd13}; //32'b10010001001110000001110;
	63'h05C: Data = {11'b11111000010, 9'b0, 2'b0, 5'd31, 5'd13}; //32'b11111000000000011010111100000;
	//63'h058: Data = 32'b11111000010000010100111100000;
	
	default: Data = 32'hXXXXXXXX;
      endcase
   end
endmodule

SingleCycleProc.v
`timescale 1ns / 1ps

module singlecycle(
		   input 	     resetl,
		   input [63:0]      startpc,
		   output reg [63:0] currentpc,
		   output [63:0]     MemtoRegOut,  // this should be attached to the output of the MemtoReg Mux
		   input 	     CLK
		   );

   // Next PC connections
   wire [63:0] 			     nextpc;       // The next PC, to be updated on clock cycle

   // Instruction Memory connections
   wire [31:0] 			     instruction;  // The current instruction

   // Parts of instruction
   wire [4:0] 			     rd;            // The destination register
   wire [4:0] 			     rm;            // Operand 1
   wire [4:0] 			     rn;            // Operand 2
   wire [10:0] 			     opcode;

   // Control wires
   wire 			     reg2loc;
   wire 			     alusrc;
   wire 			     mem2reg;
   wire 			     regwrite;
   wire 			     memread;
   wire 			     memwrite;
   wire 			     branch;
   wire 			     uncond_branch;
   wire [3:0] 			     aluctrl;
   wire [2:0] 			     signop;

   // Register file connections
   wire [63:0] 			     regoutA;     // Output A
   wire [63:0] 			     regoutB;     // Output B

   // ALU connections
   wire [63:0] 			     aluout;
   wire 			     zero;

   // Sign Extender connections
   wire [63:0] 			     extimm;
   
   wire [63:0] chosenALU; // I added this
   wire [63:0] chosenMD; // this one too for datamem

   // PC update logic
   always @(negedge CLK)
     begin
        if (resetl)
          currentpc <= #3 nextpc;
        else
          currentpc <= #3 startpc;
     end

   // Parts of instruction
   assign rd = instruction[4:0];
   assign rm = instruction[9:5];
   assign rn = reg2loc ? instruction[4:0] : instruction[20:16];
   assign opcode = instruction[31:21];

   InstructionMemory imem(
			  .Data(instruction),
			  .Address(currentpc)
			  );

   control control(
		   .reg2loc(reg2loc),
		   .alusrc(alusrc),
		   .mem2reg(mem2reg),
		   .regwrite(regwrite),
		   .memread(memread),
		   .memwrite(memwrite),
		   .branch(branch),
		   .uncond_branch(uncond_branch),
		   .aluop(aluctrl),
		   .signop(signop),
		   .opcode(opcode)
		   );

   /*
    * Connect the remaining datapath elements below.
    * Do not forget any additional multiplexers that may be required.
    */
    
   SignExtender SignExtender(
		  .OutBus(extimm), 
		  .Imm26(instruction[25:0]), 
		  .Ctrl(signop)
		  ); 
	
   RegisterFile regfile(
		  .BusA(regoutA), 
		  .BusB(regoutB), 
		  .BusW(MemtoRegOut), 
		  .RW(rd),
		  .RA(rm),
		  .RB(rn),
		  .RegWr(regwrite), 
		  .Clk(CLK)
		  );
   
   
   assign chosenALU = alusrc ? extimm : regoutB;
   ALU alu(
		  .BusW(aluout), 
		  .BusA(regoutA), 
		  .BusB(chosenALU), 
		  .ALUCtrl(aluctrl), 
		  .Zero(zero)
		  );
		  
   NextPClogic nplogic(
		  .NextPC(nextpc), 
		  .CurrentPC(currentpc), 
		  .SignExtImm64(extimm), 
		  .Branch(branch), 
		  .ALUZero(zero), 
		  .Uncondbranch(uncond_branch)
		  );
		  
   DataMemory datamemory( // figure out what ReadData is
		  .ReadData(chosenMD), 
		  .Address(aluout), 
		  .WriteData(regoutB), 
		  .MemoryRead(memread), 
		  .MemoryWrite(memwrite), 
		  .Clock(CLK)
		  );
   
   // mux between ReadData and aluout to MemtoRegOut
    
   assign MemtoRegOut = mem2reg ? chosenMD : aluout;


endmodule

SingleCycleProcTest.v
`timescale 1ns / 1ps

`define STRLEN 32
`define HalfClockPeriod 60
`define ClockPeriod `HalfClockPeriod * 2

module SingleCycleProcTest_v;

   initial
     begin
        $dumpfile("singlecycle.vcd");
        $dumpvars;
     end

   // These tasks are used to check if a given test has passed and
   // confirm that all tests passed.
   task passTest;
      input [63:0] actualOut, expectedOut;
      input [`STRLEN*8:0] testType;
      inout [7:0] 	  passed;

      if(actualOut == expectedOut) begin $display ("%s passed", testType); passed = passed + 1; end
      else $display ("%s failed: 0x%x should be 0x%x", testType, actualOut, expectedOut);
   endtask

   task allPassed;
      input [7:0] passed;
      input [7:0] numTests;

      if(passed == numTests) $display ("All tests passed");
      else $display("Some tests failed: %d of %d passed", passed, numTests);
   endtask

   // Inputs
   reg 		  CLK;
   reg 		  Reset_L;
   reg [63:0] 	  startPC;
   reg [7:0] 	  passed;
   reg [15:0] 	  watchdog;

   // Outputs
   wire [63:0] 	  MemtoRegOut;
   wire [63:0] 	  currentPC;

   // Instantiate the Unit Under Test (UUT)
   singlecycle uut (
		    .CLK(CLK),
		    .resetl(Reset_L),
		    .startpc(startPC),
		    .currentpc(currentPC),
		    .MemtoRegOut(MemtoRegOut)
		    );

   initial begin
      // Initialize Inputs
      Reset_L = 1;
      startPC = 0;
      passed = 0;

      // Initialize Watchdog timer
      watchdog = 0;

      // Wait for global reset
      #(1 * `ClockPeriod);

      // Program 1
      #1
        Reset_L = 0; startPC = 0;
      @(posedge CLK);
      @(negedge CLK);
      @(posedge CLK);
      Reset_L = 1;

      // ***********************************************************
      // This while loop will continue cycling the processor until the
      // PC reaches the final instruction in the first test.  If the
      // program forms an infinite loop, never reaching the end, the
      // watchdog timer will kick in and kill simulation after 64K
      // cycles.
      // ***********************************************************

      while (currentPC < 64'h30)
        begin
	   @(posedge CLK);
	   @(negedge CLK);
           $display("CurrentPC:%h MemtoRegOut = %h",currentPC, MemtoRegOut);
        end
      
      passTest(MemtoRegOut, 64'hF, "Results of Program 1", passed);

      // ***********************************************************
      // Add your new tests here
      // ***********************************************************      
      while (currentPC < 64'h5C)
        begin
	   @(posedge CLK);
	   @(negedge CLK);
           $display("CurrentPC:%h MemtoRegOut = %h",currentPC, MemtoRegOut);
        end
      
      passTest(MemtoRegOut, 64'h123456789abcdef0, "Results of Program 2", passed);

      // Done
      allPassed(passed, 2);   // Be sure to change the one to match
      // the number of tests you add.
      $finish;
   end

   // Initialize the clock to be 0
   initial begin
      CLK = 0;
   end

   // The following is correct if clock starts at LOW level at StartTime //
   always begin
      #`HalfClockPeriod CLK = ~CLK;
      #`HalfClockPeriod CLK = ~CLK;
      watchdog = watchdog +1;
   end

   // Kill the simulation if the watchdog hits 64K cycles
   always @*
     if (watchdog == 16'hFF)
       begin
          $display("Watchdog Timer Expired.");
          $finish;
       end


endmodule

singlecycle.vcd
$date
	Thu Apr 27 22:07:04 2023
$end
$version
	Icarus Verilog
$end
$timescale
	1ps
$end
$scope module SingleCycleProcTest_v $end
$var wire 64 ! currentPC [63:0] $end
$var wire 64 " MemtoRegOut [63:0] $end
$var reg 1 # CLK $end
$var reg 1 $ Reset_L $end
$var reg 8 % passed [7:0] $end
$var reg 64 & startPC [63:0] $end
$var reg 16 ' watchdog [15:0] $end
$scope module uut $end
$var wire 1 # CLK $end
$var wire 1 $ resetl $end
$var wire 64 ( startpc [63:0] $end
$var wire 1 ) zero $end
$var wire 1 * uncond_branch $end
$var wire 3 + signop [2:0] $end
$var wire 5 , rn [4:0] $end
$var wire 5 - rm [4:0] $end
$var wire 1 . regwrite $end
$var wire 64 / regoutB [63:0] $end
$var wire 64 0 regoutA [63:0] $end
$var wire 1 1 reg2loc $end
$var wire 5 2 rd [4:0] $end
$var wire 11 3 opcode [10:0] $end
$var wire 64 4 nextpc [63:0] $end
$var wire 1 5 memwrite $end
$var wire 1 6 memread $end
$var wire 1 7 mem2reg $end
$var wire 32 8 instruction [31:0] $end
$var wire 64 9 extimm [63:0] $end
$var wire 64 : chosenMD [63:0] $end
$var wire 64 ; chosenALU [63:0] $end
$var wire 1 < branch $end
$var wire 1 = alusrc $end
$var wire 64 > aluout [63:0] $end
$var wire 4 ? aluctrl [3:0] $end
$var wire 64 @ MemtoRegOut [63:0] $end
$var reg 64 A currentpc [63:0] $end
$scope module SignExtender $end
$var wire 26 B Imm26 [25:0] $end
$var wire 3 C Ctrl [2:0] $end
$var reg 64 D OutBus [63:0] $end
$upscope $end
$scope module alu $end
$var wire 64 E BusB [63:0] $end
$var wire 1 ) Zero $end
$var wire 64 F BusA [63:0] $end
$var wire 4 G ALUCtrl [3:0] $end
$var reg 64 H BusW [63:0] $end
$upscope $end
$scope module control $end
$var wire 11 I opcode [10:0] $end
$var reg 4 J aluop [3:0] $end
$var reg 1 = alusrc $end
$var reg 1 < branch $end
$var reg 1 7 mem2reg $end
$var reg 1 6 memread $end
$var reg 1 5 memwrite $end
$var reg 1 1 reg2loc $end
$var reg 1 . regwrite $end
$var reg 3 K signop [2:0] $end
$var reg 1 * uncond_branch $end
$upscope $end
$scope module datamemory $end
$var wire 64 L Address [63:0] $end
$var wire 1 # Clock $end
$var wire 1 6 MemoryRead $end
$var wire 1 5 MemoryWrite $end
$var wire 64 M WriteData [63:0] $end
$var reg 64 N ReadData [63:0] $end
$scope task initset $end
$var reg 64 O addr [63:0] $end
$var reg 64 P data [63:0] $end
$upscope $end
$upscope $end
$scope module imem $end
$var wire 64 Q Address [63:0] $end
$var reg 32 R Data [31:0] $end
$upscope $end
$scope module nplogic $end
$var wire 1 ) ALUZero $end
$var wire 1 < Branch $end
$var wire 64 S CurrentPC [63:0] $end
$var wire 64 T SignExtImm64 [63:0] $end
$var wire 1 * Uncondbranch $end
$var reg 64 U NextPC [63:0] $end
$upscope $end
$scope module regfile $end
$var wire 64 V BusW [63:0] $end
$var wire 1 # Clk $end
$var wire 5 W RA [4:0] $end
$var wire 5 X RB [4:0] $end
$var wire 5 Y RW [4:0] $end
$var wire 1 . RegWr $end
$var wire 64 Z BusB [63:0] $end
$var wire 64 [ BusA [63:0] $end
$upscope $end
$upscope $end
$scope task allPassed $end
$var reg 8 \ numTests [7:0] $end
$var reg 8 ] passed [7:0] $end
$upscope $end
$scope task passTest $end
$var reg 64 ^ actualOut [63:0] $end
$var reg 64 _ expectedOut [63:0] $end
$var reg 8 ` passed [7:0] $end
$var reg 257 a testType [256:0] $end
$upscope $end
$upscope $end
$enddefinitions $end
#0
$dumpvars
bx a
bx `
bx _
bx ^
bx ]
bx \
bx [
bx Z
bx Y
bx X
bx W
bx V
bx U
bx T
bx S
bx R
bx Q
b0 P
b100000 O
bx N
bx M
bx L
bx K
bx J
bx I
bx H
bx G
bx F
bx E
bx D
bx C
bx B
bx A
bx @
bx ?
bx >
x=
x<
bx ;
bx :
bx 9
bx 8
x7
x6
x5
bx 4
bx 3
bx 2
x1
bx 0
bx /
x.
bx -
bx ,
bx +
x*
x)
b0 (
b0 '
b0 &
b0 %
1$
0#
bx "
bx !
$end
#60000
1#
#120000
b1 '
0#
#121000
0$
#180000
1#
#240000
b10 '
0#
#243000
b0 ;
b0 E
b0 9
b0 D
b0 T
b1 +
b1 C
b1 K
b10 ?
b10 G
b10 J
0*
0<
05
16
1.
17
1=
b0x00x ,
b0x00x X
b10000000000001111101001 B
b11111000010 3
b11111000010 I
b11111 -
b11111 W
b1001 2
b1001 Y
b11111000010000000000001111101001 8
b11111000010000000000001111101001 R
b100 4
b100 U
b0 !
b0 A
b0 Q
b0 S
#245000
1)
b0 >
b0 H
b0 L
b0 0
b0 F
b0 [
#300000
b1 "
b1 @
b1 V
b1 :
b1 N
1$
1#
#360000
b11 '
0#
#363000
0)
b1000 >
b1000 H
b1000 L
b1000 ;
b1000 E
b1000 9
b1000 D
b1000 T
b0x0x0 ,
b0x0x0 X
b10000001000001111101010 B
b1010 2
b1010 Y
b11111000010000001000001111101010 8
b11111000010000001000001111101010 R
b1000 4
b1000 U
b100 !
b100 A
b100 Q
b100 S
#420000
b1010 "
b1010 @
b1010 V
b1010 :
b1010 N
1#
#480000
b100 '
0#
#483000
b10000 >
b10000 H
b10000 L
b10000 ;
b10000 E
b10000 9
b10000 D
b10000 T
b0x0x1 ,
b0x0x1 X
b10000010000001111101011 B
b1011 2
b1011 Y
b11111000010000010000001111101011 8
b11111000010000010000001111101011 R
b1100 4
b1100 U
b1000 !
b1000 A
b1000 Q
b1000 S
#540000
b101 "
b101 @
b101 V
b101 :
b101 N
1#
#600000
b101 '
0#
#603000
b11000 >
b11000 H
b11000 L
b11000 ;
b11000 E
b11000 9
b11000 D
b11000 T
b0xx0x ,
b0xx0x X
b10000011000001111101100 B
b1100 2
b1100 Y
b11111000010000011000001111101100 8
b11111000010000011000001111101100 R
b10000 4
b10000 U
b1100 !
b1100 A
b1100 Q
b1100 S
#660000
b111111111011111010100111110111101010110110111110111011111111 "
b111111111011111010100111110111101010110110111110111011111111 @
b111111111011111010100111110111101010110110111110111011111111 V
b111111111011111010100111110111101010110110111110111011111111 :
b111111111011111010100111110111101010110110111110111011111111 N
1#
#720000
b110 '
0#
#723000
b100000 >
b100000 H
b100000 L
b100000 ;
b100000 E
b100000 9
b100000 D
b100000 T
b0xxxx ,
b0xxxx X
b10000100000001111101101 B
b1101 2
b1101 Y
b11111000010000100000001111101101 8
b11111000010000100000001111101101 R
b10100 4
b10100 U
b10000 !
b10000 A
b10000 Q
b10000 S
#780000
b0 "
b0 @
b0 V
b0 :
b0 N
1#
#840000
b111 '
0#
#843000
x)
bx >
bx H
bx L
bx "
bx @
bx V
bx ;
bx E
bx +
bx C
bx K
b1 ?
b1 G
b1 J
06
07
0=
01
b1011 ,
b1011 X
b10000010110000000101001010 B
b10101010000 3
b10101010000 I
b1010 -
b1010 W
b1010 2
b1010 Y
b10101010000010110000000101001010 8
b10101010000010110000000101001010 R
b11000 4
b11000 U
b10100 !
b10100 A
b10100 Q
b10100 S
#845000
b1111 "
b1111 @
b1111 V
b101 ;
b101 E
0)
b1111 >
b1111 H
b1111 L
b101 /
b101 M
b101 Z
b1010 0
b1010 F
b1010 [
#900000
1#
#960000
b1000 '
0#
#963000
b0 "
b0 @
b0 V
1)
b0 >
b0 H
b0 L
b0 ?
b0 G
b0 J
b1010 ,
b1010 X
b10000010100000000110001100 B
b10001010000 3
b10001010000 I
b1100 -
b1100 W
b1100 2
b1100 Y
b10001010000010100000000110001100 8
b10001010000010100000000110001100 R
b11100 4
b11100 U
b11000 !
b11000 A
b11000 Q
b11000 S
#965000
b1111 "
b1111 @
b1111 V
b1111 ;
b1111 E
0)
b1111 >
b1111 H
b1111 L
b1111 /
b1111 M
b1111 Z
b111111111011111010100111110111101010110110111110111011111111 0
b111111111011111010100111110111101010110110111110111011111111 F
b111111111011111010100111110111101010110110111110111011111111 [
#1020000
1#
#1080000
b1001 '
0#
#1083000
b0xxxx "
b0xxxx @
b0xxxx V
b100 9
b100 D
b100 T
b11 +
b11 C
b11 K
b111 ?
b111 G
b111 J
1<
0.
x7
11
b1100 ,
b1100 X
b10001100 B
b10110100000 3
b10110100000 I
b100 -
b100 W
b10110100000000000000000010001100 8
b10110100000000000000000010001100 R
b100000 4
b100000 U
b11100 !
b11100 A
b11100 Q
b11100 S
#1085000
bx 0
bx F
bx [
#1140000
1#
#1200000
b1010 '
0#
#1203000
x)
bx >
bx H
bx L
bx "
bx @
bx V
b0xx +
b0xx C
b0xx K
b10 ?
b10 G
b10 J
0<
1.
07
01
b1001 ,
b1001 X
b11000010010000000110101101 B
b10001011000 3
b10001011000 I
b1101 -
b1101 W
b1101 2
b1101 Y
b10001011000010010000000110101101 8
b10001011000010010000000110101101 R
b100100 4
b100100 U
b100000 !
b100000 A
b100000 Q
b100000 S
